pyvigicrues/__init__.py
pyvigicrues/__main__.py
pyvigicrues/client.py
pyvigicrues-0.0.1.dist-info/LICENSE
pyvigicrues-0.0.1.dist-info/METADATA
pyvigicrues-0.0.1.dist-info/WHEEL
pyvigicrues-0.0.1.dist-info/entry_points.txt
pyvigicrues-0.0.1.dist-info/top_level.txt
pyvigicrues-0.0.1.dist-info/RECORD
