Metadata-Version: 2.1
Name: pyvigicrues
Version: 0.0.1
Summary: Get level and speed from many French rivers (https://www.vigicrues.gouv.fr/)
Home-page: https://github.com/Mickaelh51/pyVigicrues
Author: Mickael HUBERT
Author-email: github@winlux.fr
License: MIT
Platform: UNKNOWN
Classifier: Programming Language :: Python :: 3.5
Classifier: Programming Language :: Python :: 3.6
Requires-Dist: requests
